<?xml version="1.0" encoding="UTF-8" ?>
<!DOCTYPE mapper PUBLIC "-//mybatis.org//DTD Mapper 3.0//EN" "http://mybatis.org/dtd/mybatis-3-mapper.dtd" >
<mapper namespace="com.yhz.idservice.mapper.IdMapper" >
  <resultMap id="BaseResultMap" type="com.yhz.idservice.entity.Id" >
    <!--
      WARNING - @mbggenerated
      This element is automatically generated by MyBatis Generator, do not modify.
      This element was generated on Sun May 10 20:15:22 CST 2020.
    -->
    <id column="id" property="id" jdbcType="INTEGER" />
    <result column="name" property="name" jdbcType="VARCHAR" />
    <result column="age" property="age" jdbcType="INTEGER" />
    <result column="gender" property="gender" jdbcType="CHAR" />
    <result column="id_no" property="idNo" jdbcType="VARCHAR" />
    <result column="phone_number" property="phoneNumber" jdbcType="VARCHAR" />
    <result column="is_deleted" property="isDeleted" jdbcType="TINYINT" />
  </resultMap>
  <sql id="Example_Where_Clause" >
    <!--
      WARNING - @mbggenerated
      This element is automatically generated by MyBatis Generator, do not modify.
      This element was generated on Sun May 10 20:15:22 CST 2020.
    -->
    <where >
      <foreach collection="oredCriteria" item="criteria" separator="or" >
        <if test="criteria.valid" >
          <trim prefix="(" suffix=")" prefixOverrides="and" >
            <foreach collection="criteria.criteria" item="criterion" >
              <choose >
                <when test="criterion.noValue" >
                  and ${criterion.condition}
                </when>
                <when test="criterion.singleValue" >
                  and ${criterion.condition} #{criterion.value}
                </when>
                <when test="criterion.betweenValue" >
                  and ${criterion.condition} #{criterion.value} and #{criterion.secondValue}
                </when>
                <when test="criterion.listValue" >
                  and ${criterion.condition}
                  <foreach collection="criterion.value" item="listItem" open="(" close=")" separator="," >
                    #{listItem}
                  </foreach>
                </when>
              </choose>
            </foreach>
          </trim>
        </if>
      </foreach>
    </where>
  </sql>
  <sql id="Update_By_Example_Where_Clause" >
    <!--
      WARNING - @mbggenerated
      This element is automatically generated by MyBatis Generator, do not modify.
      This element was generated on Sun May 10 20:15:22 CST 2020.
    -->
    <where >
      <foreach collection="example.oredCriteria" item="criteria" separator="or" >
        <if test="criteria.valid" >
          <trim prefix="(" suffix=")" prefixOverrides="and" >
            <foreach collection="criteria.criteria" item="criterion" >
              <choose >
                <when test="criterion.noValue" >
                  and ${criterion.condition}
                </when>
                <when test="criterion.singleValue" >
                  and ${criterion.condition} #{criterion.value}
                </when>
                <when test="criterion.betweenValue" >
                  and ${criterion.condition} #{criterion.value} and #{criterion.secondValue}
                </when>
                <when test="criterion.listValue" >
                  and ${criterion.condition}
                  <foreach collection="criterion.value" item="listItem" open="(" close=")" separator="," >
                    #{listItem}
                  </foreach>
                </when>
              </choose>
            </foreach>
          </trim>
        </if>
      </foreach>
    </where>
  </sql>
  <sql id="Base_Column_List" >
    <!--
      WARNING - @mbggenerated
      This element is automatically generated by MyBatis Generator, do not modify.
      This element was generated on Sun May 10 20:15:22 CST 2020.
    -->
    id, `name`, age, gender, id_no, phone_number, is_deleted
  </sql>
  <select id="selectByExample" resultMap="BaseResultMap" parameterType="com.yhz.idservice.entity.IdExample" >
    <!--
      WARNING - @mbggenerated
      This element is automatically generated by MyBatis Generator, do not modify.
      This element was generated on Sun May 10 20:15:22 CST 2020.
    -->
    select
    <if test="distinct" >
      distinct
    </if>
    <include refid="Base_Column_List" />
    from idm_id
    <if test="_parameter != null" >
      <include refid="Example_Where_Clause" />
    </if>
    <if test="orderByClause != null" >
      order by ${orderByClause}
    </if>
  </select>
  <select id="selectByPrimaryKey" resultMap="BaseResultMap" parameterType="java.lang.Integer" >
    <!--
      WARNING - @mbggenerated
      This element is automatically generated by MyBatis Generator, do not modify.
      This element was generated on Sun May 10 20:15:22 CST 2020.
    -->
    select 
    <include refid="Base_Column_List" />
    from idm_id
    where id = #{id,jdbcType=INTEGER}
  </select>
  <delete id="deleteByPrimaryKey" parameterType="java.lang.Integer" >
    <!--
      WARNING - @mbggenerated
      This element is automatically generated by MyBatis Generator, do not modify.
      This element was generated on Sun May 10 20:15:22 CST 2020.
    -->
    delete from idm_id
    where id = #{id,jdbcType=INTEGER}
  </delete>
  <insert id="insert" parameterType="com.yhz.idservice.entity.Id" >
    <!--
      WARNING - @mbggenerated
      This element is automatically generated by MyBatis Generator, do not modify.
      This element was generated on Sun May 10 20:15:22 CST 2020.
    -->
    <selectKey resultType="java.lang.Integer" keyProperty="id" order="AFTER" >
      SELECT LAST_INSERT_ID()
    </selectKey>
    insert into idm_id (`name`, age, gender, 
      id_no, phone_number, is_deleted
      )
    values (#{name,jdbcType=VARCHAR}, #{age,jdbcType=INTEGER}, #{gender,jdbcType=CHAR}, 
      #{idNo,jdbcType=VARCHAR}, #{phoneNumber,jdbcType=VARCHAR}, #{isDeleted,jdbcType=TINYINT}
      )
  </insert>
  <insert id="insertSelective" parameterType="com.yhz.idservice.entity.Id" >
    <!--
      WARNING - @mbggenerated
      This element is automatically generated by MyBatis Generator, do not modify.
      This element was generated on Sun May 10 20:15:22 CST 2020.
    -->
    <selectKey resultType="java.lang.Integer" keyProperty="id" order="AFTER" >
      SELECT LAST_INSERT_ID()
    </selectKey>
    insert into idm_id
    <trim prefix="(" suffix=")" suffixOverrides="," >
      <if test="name != null" >
        `name`,
      </if>
      <if test="age != null" >
        age,
      </if>
      <if test="gender != null" >
        gender,
      </if>
      <if test="idNo != null" >
        id_no,
      </if>
      <if test="phoneNumber != null" >
        phone_number,
      </if>
      <if test="isDeleted != null" >
        is_deleted,
      </if>
    </trim>
    <trim prefix="values (" suffix=")" suffixOverrides="," >
      <if test="name != null" >
        #{name,jdbcType=VARCHAR},
      </if>
      <if test="age != null" >
        #{age,jdbcType=INTEGER},
      </if>
      <if test="gender != null" >
        #{gender,jdbcType=CHAR},
      </if>
      <if test="idNo != null" >
        #{idNo,jdbcType=VARCHAR},
      </if>
      <if test="phoneNumber != null" >
        #{phoneNumber,jdbcType=VARCHAR},
      </if>
      <if test="isDeleted != null" >
        #{isDeleted,jdbcType=TINYINT},
      </if>
    </trim>
  </insert>
  <select id="countByExample" parameterType="com.yhz.idservice.entity.IdExample" resultType="java.lang.Integer" >
    <!--
      WARNING - @mbggenerated
      This element is automatically generated by MyBatis Generator, do not modify.
      This element was generated on Sun May 10 20:15:22 CST 2020.
    -->
    select count(*) from idm_id
    <if test="_parameter != null" >
      <include refid="Example_Where_Clause" />
    </if>
  </select>
  <update id="updateByExampleSelective" parameterType="map" >
    <!--
      WARNING - @mbggenerated
      This element is automatically generated by MyBatis Generator, do not modify.
      This element was generated on Sun May 10 20:15:22 CST 2020.
    -->
    update idm_id
    <set >
      <if test="record.id != null" >
        id = #{record.id,jdbcType=INTEGER},
      </if>
      <if test="record.name != null" >
        `name` = #{record.name,jdbcType=VARCHAR},
      </if>
      <if test="record.age != null" >
        age = #{record.age,jdbcType=INTEGER},
      </if>
      <if test="record.gender != null" >
        gender = #{record.gender,jdbcType=CHAR},
      </if>
      <if test="record.idNo != null" >
        id_no = #{record.idNo,jdbcType=VARCHAR},
      </if>
      <if test="record.phoneNumber != null" >
        phone_number = #{record.phoneNumber,jdbcType=VARCHAR},
      </if>
      <if test="record.isDeleted != null" >
        is_deleted = #{record.isDeleted,jdbcType=TINYINT},
      </if>
    </set>
    <if test="_parameter != null" >
      <include refid="Update_By_Example_Where_Clause" />
    </if>
  </update>
  <update id="updateByExample" parameterType="map" >
    <!--
      WARNING - @mbggenerated
      This element is automatically generated by MyBatis Generator, do not modify.
      This element was generated on Sun May 10 20:15:22 CST 2020.
    -->
    update idm_id
    set id = #{record.id,jdbcType=INTEGER},
      `name` = #{record.name,jdbcType=VARCHAR},
      age = #{record.age,jdbcType=INTEGER},
      gender = #{record.gender,jdbcType=CHAR},
      id_no = #{record.idNo,jdbcType=VARCHAR},
      phone_number = #{record.phoneNumber,jdbcType=VARCHAR},
      is_deleted = #{record.isDeleted,jdbcType=TINYINT}
    <if test="_parameter != null" >
      <include refid="Update_By_Example_Where_Clause" />
    </if>
  </update>
  <update id="updateByPrimaryKeySelective" parameterType="com.yhz.idservice.entity.Id" >
    <!--
      WARNING - @mbggenerated
      This element is automatically generated by MyBatis Generator, do not modify.
      This element was generated on Sun May 10 20:15:22 CST 2020.
    -->
    update idm_id
    <set >
      <if test="name != null" >
        `name` = #{name,jdbcType=VARCHAR},
      </if>
      <if test="age != null" >
        age = #{age,jdbcType=INTEGER},
      </if>
      <if test="gender != null" >
        gender = #{gender,jdbcType=CHAR},
      </if>
      <if test="idNo != null" >
        id_no = #{idNo,jdbcType=VARCHAR},
      </if>
      <if test="phoneNumber != null" >
        phone_number = #{phoneNumber,jdbcType=VARCHAR},
      </if>
      <if test="isDeleted != null" >
        is_deleted = #{isDeleted,jdbcType=TINYINT},
      </if>
    </set>
    where id = #{id,jdbcType=INTEGER}
  </update>
  <update id="updateByPrimaryKey" parameterType="com.yhz.idservice.entity.Id" >
    <!--
      WARNING - @mbggenerated
      This element is automatically generated by MyBatis Generator, do not modify.
      This element was generated on Sun May 10 20:15:22 CST 2020.
    -->
    update idm_id
    set `name` = #{name,jdbcType=VARCHAR},
      age = #{age,jdbcType=INTEGER},
      gender = #{gender,jdbcType=CHAR},
      id_no = #{idNo,jdbcType=VARCHAR},
      phone_number = #{phoneNumber,jdbcType=VARCHAR},
      is_deleted = #{isDeleted,jdbcType=TINYINT}
    where id = #{id,jdbcType=INTEGER}
  </update>
</mapper>